LICENSE.md
readme.md
setup.py
RAKEkeywords/__init__.py
RAKEkeywords.egg-info/PKG-INFO
RAKEkeywords.egg-info/SOURCES.txt
RAKEkeywords.egg-info/dependency_links.txt
RAKEkeywords.egg-info/requires.txt
RAKEkeywords.egg-info/top_level.txt