Metadata-Version: 1.0
Name: RAKEkeywords
Version: 0.2.0
Summary: Implementation of RAKE - Rapid Automatic Keyword Extraction
Home-page: https://github.com/OpenJarbas/RAKEkeywords
Author: jarbasAI
Author-email: jarbasai@mailfence.com
License: Apache2
Platform: UNKNOWN
